{"Functions": {"requestLocationUpdate()": {"Returns": [], "Parameters": [], "Throws": [], "SeeAlso": [], "Permissions": [], "Description": "Request an update of the current location. If the location has changed, a broadcast will be sent to everyone registered with @B_android#telephony#PhoneStateListener#LISTEN_CELL_LOCATION_E@.", "history": "Added in API level 1", "FullName": "public static void requestLocationUpdate ()"}, "getEmpty()": {"Returns": [["@B_android#telephony#CellLocation_E@", "no returns description in source"]], "Parameters": [], "Throws": [], "SeeAlso": [], "Permissions": [], "Description": "Return a new CellLocation object representing an unknown location, or null for unknown/none phone radio types.", "history": "Added in API level 1", "FullName": "public static CellLocation getEmpty ()"}, "CellLocation()": {"Returns": [], "Parameters": [], "Throws": [], "SeeAlso": [], "Permissions": [], "Description": "", "history": "added in API level 1", "FullName": "public CellLocation ()"}}, "Inheritance": [], "ClassName": "android.telephony.CellLocation", "ClassDesc": "Abstract class that represents the location of the device."}