{"Functions": {"onTimedText(android.media.MediaPlayer,android.media.TimedText)": {"Returns": [], "Parameters": [["@B_android#media#MediaPlayer_E@", "MediaPlayer: the MediaPlayer associated with this callback"], ["@B_android#media#TimedText_E@", "TimedText: the timed text sample which contains the text needed to be displayed and the display format."]], "Throws": [], "SeeAlso": [], "Permissions": [], "Description": "Called to indicate an avaliable timed text", "history": "Added in API level 16", "FullName": "public abstract void onTimedText (MediaPlayer mp, TimedText text)"}}, "Inheritance": [], "ClassName": "android.media.MediaPlayer.OnTimedTextListener", "ClassDesc": "Interface definition of a callback to be invoked when a timed text is available for display."}