{"Functions": {"getSupportBackgroundTintList()": {"Returns": [["@B_android#content#res#ColorStateList_E@", "the tint applied to the background drawable"]], "Parameters": [], "Throws": [], "SeeAlso": [], "Permissions": [], "Description": "Return the tint applied to the background drawable, if specified.", "history": "added in version 23.1.1", "FullName": "ColorStateList getSupportBackgroundTintList ()"}, "getSupportBackgroundTintMode()": {"Returns": [["@B_android#graphics#PorterDuff#Mode_E@", "the blending mode used to apply the tint to the background drawable"]], "Parameters": [], "Throws": [], "SeeAlso": [], "Permissions": [], "Description": "Return the blending mode used to apply the tint to the background drawable, if specified.", "history": "added in version 23.1.1", "FullName": "PorterDuff.Mode getSupportBackgroundTintMode ()"}}, "Inheritance": [], "ClassName": "android.support.v4.view.TintableBackgroundView", "ClassDesc": "Interface which allows a https:##developer#android#com@B_android#view#View_E@ to receive background tinting calls from @B_android#support#v4#view#ViewCompat_E@ when running on API v20 devices or lower."}