{"Functions": {"onRestrictedCaptionAreaChanged(android.graphics.Rect)": {"Returns": [], "Parameters": [["@B_android#graphics#Rect_E@", "Rect: The area where caption content is positioned, relative to the top view."]], "Throws": [], "SeeAlso": [], "Permissions": [], "Description": "Called when the area where caption draws content changes.", "history": "Added in API level 24", "FullName": "public abstract void onRestrictedCaptionAreaChanged (Rect rect)"}}, "Inheritance": [], "ClassName": "android.view.Window.OnRestrictedCaptionAreaChangedListener", "ClassDesc": "Callback for clients that want to be aware of where caption draws content."}