{"Functions": {"getDefaultSmsPackage(android.content.Context)": {"Returns": [["@B_java#lang#String_E@", "package name for the default SMS package or null"]], "Parameters": [["@B_android#content#Context_E@", "Context: context of the requesting application"]], "Throws": [], "SeeAlso": [], "Permissions": [], "Description": "Used to determine the currently configured default SMS package.", "history": "Added in API level 19", "FullName": "public static String getDefaultSmsPackage (Context context)"}}, "Inheritance": [], "ClassName": "android.provider.Telephony.Sms", "ClassDesc": "Contains all text-based SMS messages."}