{"Functions": {"CallbackRegistry.NotifierCallback()": {"Returns": [], "Parameters": [], "Throws": [], "SeeAlso": [], "Permissions": [], "Description": "", "history": "", "FullName": "CallbackRegistry.NotifierCallback ()"}, "onNotifyCallback(C, T, int, A)": {"Returns": [], "Parameters": [["C", "C: The callback to notify."], ["T", "T: The opaque sender object."], ["int", "int: The opaque notification parameter."], ["A", "A: An opaque argument passed in @B_android#databinding#CallbackRegistry#notifyCallbacks_E@"]], "Throws": [], "SeeAlso": ["@B_android#databinding#CallbackRegistry#CallbackRegistry_E@"], "Permissions": [], "Description": "Called by CallbackRegistry during @B_android#databinding#CallbackRegistry#notifyCallbacks_E@} to notify the callback.", "history": "", "FullName": "void onNotifyCallback (C callback, T sender, int arg, A arg2)"}}, "Inheritance": ["http:##developer#android#com@B_java#lang#Object_E@"], "ClassName": "android.databinding.CallbackRegistry.NotifierCallback<C, T, A>", "ClassDesc": "Class used to notify events from CallbackRegistry."}