{"Functions": {"run()": {"Returns": [], "Parameters": [], "Throws": [], "SeeAlso": [], "Permissions": [], "Description": "When an object implementing interface Runnable is used to create a thread, starting the thread causes the object's run method to be called in that separately executing thread. The general contract of the method run is that it may take any action whatsoever.", "history": "Added in API level 11", "FullName": "public void run ()"}, "RenderScript.RSErrorHandler()": {"Returns": [], "Parameters": [], "Throws": [], "SeeAlso": [], "Permissions": [], "Description": "", "history": "added in API level 11", "FullName": "public RenderScript.RSErrorHandler ()"}}, "Inheritance": [], "ClassName": "android.renderscript.RenderScript.RSErrorHandler", "ClassDesc": "The runtime error handler base class. An application should derive from this class if it wishes to install an error handler. When errors occur at runtime, the fields in this class will be filled, and the run method will be called."}