{"Functions": {"onError(android.media.MediaRecorder, int, int)": {"Returns": [], "Parameters": [["@B_android#media#MediaRecorder_E@", "MediaRecorder: the MediaRecorder that encountered the error"], ["int", "int: the type of error that has occurred: MediaRecorder.MEDIA_RECORDER_ERROR_UNKNOWN MediaRecorder.MEDIA_ERROR_SERVER_DIED"], ["int", "int: an extra code, specific to the error type"]], "Throws": [], "SeeAlso": [], "Permissions": [], "Description": "Called when an error occurs while recording.", "history": "added in API level 3", "FullName": "public abstract void onError (MediaRecorder mr, int what, int extra)"}, "onError(android.media.MediaRecorder,int,int)": {"Returns": [], "Parameters": [["@B_android#media#MediaRecorder_E@", "MediaRecorder: the MediaRecorder that encountered the error"], ["int", "int: the type of error that has occurred: MediaRecorder.MEDIA_RECORDER_ERROR_UNKNOWN MediaRecorder.MEDIA_ERROR_SERVER_DIED"], ["int", "int: an extra code, specific to the error type"]], "Throws": [], "SeeAlso": [], "Permissions": [], "Description": "Called when an error occurs while recording.", "history": "Added in API level 3", "FullName": "public abstract void onError (MediaRecorder mr, int what, int extra)"}}, "Inheritance": [], "ClassName": "android.media.MediaRecorder.OnErrorListener", "ClassDesc": "Interface definition for a callback to be invoked when an error occurs while recording."}