{"Functions": {"getLightVibrantSwatch()": {"Returns": [], "Parameters": [], "Throws": [], "SeeAlso": [], "Permissions": [], "Description": "Return a light and vibrant @B_android#support#v7#graphics#Palette#Swatch_E@", "history": "", "FullName": "public Palette.Swatch getLightVibrantSwatch ()"}, "getMutedSwatch()": {"Returns": [], "Parameters": [], "Throws": [], "SeeAlso": [], "Permissions": [], "Description": "Return a muted @B_android#support#v7#graphics#Palette#Swatch_E@", "history": "", "FullName": "public Palette.Swatch getMutedSwatch ()"}, "getLightMutedSwatch()": {"Returns": [], "Parameters": [], "Throws": [], "SeeAlso": [], "Permissions": [], "Description": "Return a muted and light @B_android#support#v7#graphics#Palette#Swatch_E@", "history": "", "FullName": "public Palette.Swatch getLightMutedSwatch ()"}, "getDarkMutedSwatch()": {"Returns": [], "Parameters": [], "Throws": [], "SeeAlso": [], "Permissions": [], "Description": "Return a muted and dark @B_android#support#v7#graphics#Palette#Swatch_E@", "history": "", "FullName": "public Palette.Swatch getDarkMutedSwatch ()"}, "Palette.Generator()": {"Returns": [], "Parameters": [], "Throws": [], "SeeAlso": [], "Permissions": [], "Description": "", "history": "", "FullName": "public Palette.Generator ()"}, "getVibrantSwatch()": {"Returns": [], "Parameters": [], "Throws": [], "SeeAlso": [], "Permissions": [], "Description": "Return the most vibrant @B_android#support#v7#graphics#Palette#Swatch_E@", "history": "", "FullName": "public Palette.Swatch getVibrantSwatch ()"}, "getDarkVibrantSwatch()": {"Returns": [], "Parameters": [], "Throws": [], "SeeAlso": [], "Permissions": [], "Description": "Return a dark and vibrant @B_android#support#v7#graphics#Palette#Swatch_E@", "history": "", "FullName": "public Palette.Swatch getDarkVibrantSwatch ()"}, "generate(java.util.List<android.support.v7.graphics.Palette.Swatch>)": {"Returns": [], "Parameters": [], "Throws": [], "SeeAlso": [], "Permissions": [], "Description": "This method will be called with the @B_android#support#v7#graphics#Palette#Swatch_E@ that represent an image. You should process this list so that you have appropriate values when the other methods in class are called. This method will probably be called on a background thread.", "history": "", "FullName": "public abstract void generate (List<Palette.Swatch> swatches)"}}, "Inheritance": [], "ClassName": "android.support.v7.graphics.Palette.Generator", "ClassDesc": "Extension point for @B_android#support#v7#graphics#Palette_E@ which allows custom processing of the list of @B_android#support#v7#graphics#Palette#Swatch_E@ instances which represent an image. You should do as much processing as possible during the @B_android#support#v7#graphics#Palette#Generator#generate_E@ method call. The other methods in this class may be called multiple times to retrieve an appropriate @B_android#support#v7#graphics#Palette#Swatch_E@. Usage of a custom @B_android#support#v7#graphics#Palette#Generator_E@ is done with @B_android#support#v7#graphics#Palette#Builder#generator_E@ as so:"}