{"Functions": {"getInstance()": {"Returns": [["@B_android#icu#text#ListFormatter_E@", "ListFormatter"]], "Parameters": [], "Throws": [], "SeeAlso": [], "Permissions": [], "Description": "Create a list formatter that is appropriate for the default FORMAT locale.", "history": "Added in API level 26", "FullName": "public static ListFormatter getInstance ()"}, "getInstance(android.icu.util.ULocale)": {"Returns": [["@B_android#icu#text#ListFormatter_E@", "ListFormatter"]], "Parameters": [["@B_android#icu#util#ULocale_E@", "ULocale: the locale in question."]], "Throws": [], "SeeAlso": [], "Permissions": [], "Description": "Create a list formatter that is appropriate for a locale.", "history": "Added in API level 26", "FullName": "public static ListFormatter getInstance (ULocale locale)"}, "getInstance(java.util.Locale)": {"Returns": [["@B_android#icu#text#ListFormatter_E@", "ListFormatter"]], "Parameters": [["@B_java#util#Locale_E@", "Locale: the locale in question."]], "Throws": [], "SeeAlso": [], "Permissions": [], "Description": "Create a list formatter that is appropriate for a locale.", "history": "Added in API level 26", "FullName": "public static ListFormatter getInstance (Locale locale)"}, "getPatternForNumItems(int)": {"Returns": [["@B_java#lang#String_E@", "the pattern with {0}, {1}, {2}, etc. For English, getPatternForNumItems(3) == \"{0}, {1}, and {2}\""]], "Parameters": [["int", "int: the item count."]], "Throws": [["@B_java#lang#IllegalArgumentException_E@", "when count is 0 or negative."]], "SeeAlso": [], "Permissions": [], "Description": "Returns the pattern to use for a particular item count.", "history": "Added in API level 26", "FullName": "public String getPatternForNumItems (int count)"}, "format(java.lang.Object...)": {"Returns": [["@B_java#lang#String_E@", "items formatted into a string"]], "Parameters": [["@B_java#lang#Object_E@", "Object: items to format. The toString() method is called on each."]], "Throws": [], "SeeAlso": [], "Permissions": [], "Description": "Format a list of objects.", "history": "Added in API level 26", "FullName": "public String format (Object... items)"}, "format(java.util.Collection<?>)": {"Returns": [["@B_java#lang#String_E@", "items formatted into a string"]], "Parameters": [["@B_java#util#Collection_E@", "Collection: items to format. The toString() method is called on each."]], "Throws": [], "SeeAlso": [], "Permissions": [], "Description": "Format a collection of objects. The toString() method is called on each.", "history": "Added in API level 26", "FullName": "public String format (Collection<?> items)"}}, "Inheritance": [], "ClassName": "android.icu.text.ListFormatter", "ClassDesc": "Immutable class for formatting a list, using data from CLDR (or supplied separately). The class is not subclassable."}