{"Functions": {"valueOf(java.lang.String)": {"Returns": [["@B_android#icu#text#Normalizer2#Mode_E@", "no returns description in source"]], "Parameters": [["@B_java#lang#String_E@", "String no parameter comment"]], "Throws": [], "SeeAlso": [], "Permissions": [], "Description": "", "history": "added in API level 24", "FullName": "public static Normalizer2.Mode valueOf (String name)"}, "values()": {"Returns": [["@B_android#icu#text#Normalizer2#Mode_E@", "no returns description in source"]], "Parameters": [], "Throws": [], "SeeAlso": [], "Permissions": [], "Description": "", "history": "added in API level 24", "FullName": "public static final Mode[] values ()"}}, "Inheritance": ["@B_java#lang#Enum_E@"], "ClassName": "android.icu.text.Normalizer2.Mode", "ClassDesc": "Constants for normalization modes. For details about standard Unicode normalization forms and about the algorithms which are also used with custom mapping tables see http://www.unicode.org/unicode/reports/tr15/"}