{"Functions": {"getWasLaunched()": {"Returns": [], "Parameters": [], "Throws": [], "SeeAlso": [], "Permissions": [], "Description": "Returns whether the application was freshly launched.", "history": "", "FullName": "public abstract boolean getWasLaunched ()"}, "getApplicationMetadata()": {"Returns": [], "Parameters": [], "Throws": [], "SeeAlso": [], "Permissions": [], "Description": "Returns the current application's metadata.", "history": "", "FullName": "public abstract ApplicationMetadata getApplicationMetadata ()"}, "getApplicationStatus()": {"Returns": [], "Parameters": [], "Throws": [], "SeeAlso": [], "Permissions": [], "Description": "Returns the current application's status.", "history": "", "FullName": "public abstract String getApplicationStatus ()"}, "getSessionId()": {"Returns": [], "Parameters": [], "Throws": [], "SeeAlso": [], "Permissions": [], "Description": "Returns the current application's session ID.", "history": "", "FullName": "public abstract String getSessionId ()"}}, "Inheritance": [], "ClassName": "com.google.android.gms.cast.Cast.ApplicationConnectionResult", "ClassDesc": "When a connection to a receiver application has been established, this object contains information about that application, including its @B_com#google#android#gms#cast#ApplicationMetadata_E@ and current status. If the connection fails, then all values except getStatus() will be invalid."}