{"Functions": {"writeToParcel(android.os.Parcel, int)": {"Returns": [], "Parameters": [], "Throws": [], "SeeAlso": [], "Permissions": [], "Description": "", "history": "", "FullName": "public void writeToParcel (Parcel parcel, int i)"}, "isPersisted()": {"Returns": [], "Parameters": [], "Throws": [], "SeeAlso": [], "Permissions": [], "Description": "", "history": "", "FullName": "public boolean isPersisted ()"}, "getTag()": {"Returns": [["", "The String identifier for this task, that is returned to onRunTask(com.google.android.gms.gcm.TaskParams) when this task executes."]], "Parameters": [], "Throws": [], "SeeAlso": [], "Permissions": [], "Description": "", "history": "", "FullName": "public String getTag ()"}, "getServiceName()": {"Returns": [["", "The GcmTaskService component that this task will execute on."]], "Parameters": [], "Throws": [], "SeeAlso": [], "Permissions": [], "Description": "", "history": "", "FullName": "public String getServiceName ()"}, "isUpdateCurrent()": {"Returns": [["", "Whether or not this task will update a pre-existing task in the scheduler queue."]], "Parameters": [], "Throws": [], "SeeAlso": [], "Permissions": [], "Description": "", "history": "", "FullName": "public boolean isUpdateCurrent ()"}, "describeContents()": {"Returns": [], "Parameters": [], "Throws": [], "SeeAlso": [], "Permissions": [], "Description": "", "history": "", "FullName": "public int describeContents ()"}}, "Inheritance": ["java.lang.Object"], "ClassName": "com.google.android.gms.gcm.Task", "ClassDesc": "Encapsulates the parameters of a task that you will schedule on the GcmNetworkManager. Construct instances of either PeriodicTask or OneoffTask with the desired parameters/behaviour and schedule them using schedule(Task)."}