{"Functions": {"LaunchOptions.Builder()": {"Returns": [], "Parameters": [], "Throws": [], "SeeAlso": [], "Permissions": [], "Description": "Constructs a new @B_com#google#android#gms#cast#LaunchOptions#Builder_E@.", "history": "", "FullName": "public LaunchOptions.Builder ()"}, "build()": {"Returns": [], "Parameters": [], "Throws": [], "SeeAlso": [], "Permissions": [], "Description": "Builds and returns the @B_com#google#android#gms#cast#LaunchOptions_E@ object.", "history": "", "FullName": "public LaunchOptions build ()"}, "setLocale(java.util.Locale)": {"Returns": [], "Parameters": [], "Throws": [], "SeeAlso": [], "Permissions": [], "Description": "Sets the desired application locale.", "history": "", "FullName": "public LaunchOptions.Builder setLocale (Locale locale)"}, "setRelaunchIfRunning(boolean)": {"Returns": [], "Parameters": [], "Throws": [], "SeeAlso": [], "Permissions": [], "Description": "Sets the \"relaunch if running\" flag.", "history": "", "FullName": "public LaunchOptions.Builder setRelaunchIfRunning (boolean relaunchIfRunning)"}}, "Inheritance": ["java.lang.Object"], "ClassName": "com.google.android.gms.cast.LaunchOptions.Builder", "ClassDesc": "A builder for @B_com#google#android#gms#cast#LaunchOptions_E@ objects."}