{"Functions": {"onFinish()": {"Returns": [], "Parameters": [], "Throws": [], "SeeAlso": [], "Permissions": [], "Description": "Invoked when a task is complete.", "history": "", "FullName": "public abstract void onFinish ()"}, "onCancel()": {"Returns": [], "Parameters": [], "Throws": [], "SeeAlso": [], "Permissions": [], "Description": "Invoked when a task is cancelled.", "history": "", "FullName": "public abstract void onCancel ()"}}, "Inheritance": [], "ClassName": "com.google.android.gms.maps.GoogleMap.CancelableCallback", "ClassDesc": "A callback interface for reporting when a task is complete or cancelled."}