{"Functions": {"onDataPoint(com.google.android.gms.fitness.data.DataPoint)": {"Returns": [], "Parameters": [["@B_com#google#android#gms#fitness#data#DataPoint_E@", "the data point for this event"]], "Throws": [], "SeeAlso": [], "Permissions": [], "Description": "Handle a new data point from the data source. The data point's", "history": "", "FullName": "public abstract void onDataPoint (DataPoint dataPoint)"}}, "Inheritance": [], "ClassName": "com.google.android.gms.fitness.request.OnDataPointListener", "ClassDesc": "Listener used to register to live data updates from a @B_com#google#android#gms#fitness#data#DataSource_E@. Used by clients wanting to subscribe to live data stream updates via @B_com#google#android#gms#fitness#SensorsApi_E@. Each event is delivered as a @B_com#google#android#gms#fitness#data#DataPoint_E@. The listener is used both when"}