{"Functions": {"width(float)": {"Returns": [["", "this @B_com#google#android#gms#maps#model#PolylineOptions_E@ object with a new width set."]], "Parameters": [], "Throws": [], "SeeAlso": [], "Permissions": [], "Description": "Sets the width of the polyline in screen pixels. The default is 10.", "history": "", "FullName": "public PolylineOptions width (float width)"}, "add(com.google.android.gms.maps.model.LatLng...)": {"Returns": [["", "this @B_com#google#android#gms#maps#model#PolylineOptions_E@ object with the given points on the end."]], "Parameters": [], "Throws": [], "SeeAlso": [], "Permissions": [], "Description": "Adds vertices to the end of the polyline being built.", "history": "", "FullName": "public PolylineOptions add (LatLng... points)"}, "geodesic(boolean)": {"Returns": [["", "this @B_com#google#android#gms#maps#model#PolylineOptions_E@ object with a new geodesic setting."]], "Parameters": [], "Throws": [], "SeeAlso": [], "Permissions": [], "Description": "Specifies whether to draw each segment of this polyline as a geodesic. The default setting is false", "history": "", "FullName": "public PolylineOptions geodesic (boolean geodesic)"}, "describeContents()": {"Returns": [], "Parameters": [], "Throws": [], "SeeAlso": [], "Permissions": [], "Description": "", "history": "", "FullName": "public int describeContents ()"}, "visible(boolean)": {"Returns": [["", "this @B_com#google#android#gms#maps#model#PolylineOptions_E@ object with a new visibility setting."]], "Parameters": [], "Throws": [], "SeeAlso": [], "Permissions": [], "Description": "Specifies the visibility for the polyline. The default visibility is true.", "history": "", "FullName": "public PolylineOptions visible (boolean visible)"}, "isVisible()": {"Returns": [["", "true if the polyline is to be visible; false if it is not."]], "Parameters": [], "Throws": [], "SeeAlso": [], "Permissions": [], "Description": "Gets the visibility setting for this Options object.", "history": "", "FullName": "public boolean isVisible ()"}, "getColor()": {"Returns": [["", "the color of the polyline in ARGB format."]], "Parameters": [], "Throws": [], "SeeAlso": [], "Permissions": [], "Description": "Gets the color set for this Options object.", "history": "", "FullName": "public int getColor ()"}, "color(int)": {"Returns": [["", "this @B_com#google#android#gms#maps#model#PolylineOptions_E@ object with a new color set."]], "Parameters": [], "Throws": [], "SeeAlso": [], "Permissions": [], "Description": "Sets the color of the polyline as a 32-bit ARGB color. The default color is black ( 0xff000000).", "history": "", "FullName": "public PolylineOptions color (int color)"}, "writeToParcel(android.os.Parcel, int)": {"Returns": [], "Parameters": [], "Throws": [], "SeeAlso": [], "Permissions": [], "Description": "", "history": "", "FullName": "public void writeToParcel (Parcel out, int flags)"}, "PolylineOptions()": {"Returns": [], "Parameters": [], "Throws": [], "SeeAlso": [], "Permissions": [], "Description": "", "history": "", "FullName": "public PolylineOptions ()"}, "addAll(java.lang.Iterable<com.google.android.gms.maps.model.LatLng>)": {"Returns": [["", "this @B_com#google#android#gms#maps#model#PolylineOptions_E@ object with the given points on the end."]], "Parameters": [], "Throws": [], "SeeAlso": [], "Permissions": [], "Description": "Adds vertices to the end of the polyline being built.", "history": "", "FullName": "public PolylineOptions addAll (Iterable<LatLng> points)"}, "zIndex(float)": {"Returns": [["", "this @B_com#google#android#gms#maps#model#PolylineOptions_E@ object with a new zIndex set."]], "Parameters": [], "Throws": [], "SeeAlso": [], "Permissions": [], "Description": "Specifies the polyline's zIndex, i.e., the order in which it will be drawn. See the documentation at the top of this class for more information about zIndex.", "history": "", "FullName": "public PolylineOptions zIndex (float zIndex)"}, "getZIndex()": {"Returns": [["", "the zIndex of the polyline."]], "Parameters": [], "Throws": [], "SeeAlso": [], "Permissions": [], "Description": "Gets the zIndex set for this Options object.", "history": "", "FullName": "public float getZIndex ()"}, "getWidth()": {"Returns": [["", "the width of the polyline in screen pixels."]], "Parameters": [], "Throws": [], "SeeAlso": [], "Permissions": [], "Description": "Gets the width set for this Options object.", "history": "", "FullName": "public float getWidth ()"}, "getPoints()": {"Returns": [["", "the list of @B_com#google#android#gms#maps#model#LatLng_E@s specifying the vertices of the polyline."]], "Parameters": [], "Throws": [], "SeeAlso": [], "Permissions": [], "Description": "Gets the points set for this Options object.", "history": "", "FullName": "public List<LatLng> getPoints ()"}, "add(com.google.android.gms.maps.model.LatLng)": {"Returns": [["", "this @B_com#google#android#gms#maps#model#PolylineOptions_E@ object with the given point on the end."]], "Parameters": [], "Throws": [], "SeeAlso": [], "Permissions": [], "Description": "Adds a vertex to the end of the polyline being built.", "history": "", "FullName": "public PolylineOptions add (LatLng point)"}, "isGeodesic()": {"Returns": [["", "true if the polyline segments should be geodesics; false they should not be."]], "Parameters": [], "Throws": [], "SeeAlso": [], "Permissions": [], "Description": "Gets the geodesic setting for this Options object.", "history": "", "FullName": "public boolean isGeodesic ()"}}, "Inheritance": ["java.lang.Object"], "ClassName": "com.google.android.gms.maps.model.PolylineOptions", "ClassDesc": "Defines options for a polyline. For more information, read the"}