{"Functions": {"values()": {"Returns": [["@B_java#time#chrono#IsoEra_E@", "no returns description in source"]], "Parameters": [], "Throws": [], "SeeAlso": [], "Permissions": [], "Description": "", "history": "added in API level 26", "FullName": "public static final IsoEra[] values ()"}, "of(int)": {"Returns": [["@B_java#time#chrono#IsoEra_E@", "the era singleton, not null"]], "Parameters": [["int", "int: the BCE/CE value to represent, from 0 (BCE) to 1 (CE)"]], "Throws": [["@B_java#time#DateTimeException_E@", "if the value is invalid"]], "SeeAlso": [], "Permissions": [], "Description": "Obtains an instance of IsoEra from an int value. IsoEra is an enum representing the ISO eras of BCE/CE. This factory allows the enum to be obtained from the int value.", "history": "Added in API level 26", "FullName": "public static IsoEra of (int isoEra)"}, "getValue()": {"Returns": [["int", "the era value, from 0 (BCE) to 1 (CE)"]], "Parameters": [], "Throws": [], "SeeAlso": [], "Permissions": [], "Description": "Gets the numeric era int value. The era BCE has the value 0, while the era CE has the value 1.", "history": "Added in API level 26", "FullName": "public int getValue ()"}, "valueOf(java.lang.String)": {"Returns": [["@B_java#time#chrono#IsoEra_E@", "no returns description in source"]], "Parameters": [["@B_java#lang#String_E@", "String no parameter comment"]], "Throws": [], "SeeAlso": [], "Permissions": [], "Description": "", "history": "added in API level 26", "FullName": "public static IsoEra valueOf (String name)"}}, "Inheritance": ["@B_java#lang#Enum_E@"], "ClassName": "java.time.chrono.IsoEra", "ClassDesc": "An era in the ISO calendar system. The ISO-8601 standard does not define eras. A definition has therefore been created with two eras - 'Current era' (CE) for years on or after 0001-01-01 (ISO), and 'Before current era' (BCE) for years before that."}