{"Functions": {"setForcedRoute(org.apache.http.conn.routing.HttpRoute)": {"Returns": [], "Parameters": [], "Throws": [], "SeeAlso": ["@B_org#apache#http#conn#params#ConnRoutePNames_E@"], "Permissions": [], "Description": "", "history": "Added in API level 1", "FullName": "public void setForcedRoute (HttpRoute route)"}, "setLocalAddress(java.net.InetAddress)": {"Returns": [], "Parameters": [], "Throws": [], "SeeAlso": ["@B_org#apache#http#conn#params#ConnRoutePNames_E@"], "Permissions": [], "Description": "", "history": "Added in API level 1", "FullName": "public void setLocalAddress (InetAddress address)"}, "ConnRouteParamBean(org.apache.http.params.HttpParams)": {"Returns": [], "Parameters": [], "Throws": [], "SeeAlso": [], "Permissions": [], "Description": "", "history": "Added in API level 1", "FullName": "public ConnRouteParamBean (HttpParams params)"}, "setDefaultProxy(org.apache.http.HttpHost)": {"Returns": [], "Parameters": [], "Throws": [], "SeeAlso": ["@B_org#apache#http#conn#params#ConnRoutePNames_E@"], "Permissions": [], "Description": "", "history": "Added in API level 1", "FullName": "public void setDefaultProxy (HttpHost defaultProxy)"}}, "Inheritance": ["@B_org#apache#http#params#HttpAbstractParamBean_E@"], "ClassName": "org.apache.http.conn.params.ConnRouteParamBean", "ClassDesc": "Please use @B_java#net#URL#openConnection_E@ instead. Please visit Allows for setting parameters relating to connection routes on @B_org#apache#http#params#HttpParams_E@. This class ensures that the values set on the params are type-safe."}