{"Functions": {"nextElement()": {"Returns": [["", "the next header element in this iteration"]], "Parameters": [], "Throws": [], "SeeAlso": [], "Permissions": [], "Description": "Obtains the next header element from this iteration. This method should only be called while @B_org#apache#http#HeaderElementIterator#hasNext_E@ is true.", "history": "Added in API level 1", "FullName": "public abstract HeaderElement nextElement ()"}, "hasNext()": {"Returns": [["", "true if there is another header element, false otherwise"]], "Parameters": [], "Throws": [], "SeeAlso": [], "Permissions": [], "Description": "Indicates whether there is another header element in this iteration.", "history": "Added in API level 1", "FullName": "public abstract boolean hasNext ()"}}, "Inheritance": [], "ClassName": "org.apache.http.HeaderElementIterator", "ClassDesc": "Please use @B_java#net#URL#openConnection_E@ instead. Please visit A type-safe iterator for @B_org#apache#http#HeaderElement_E@ objects."}