{"Functions": {"getContent()": {"Returns": [], "Parameters": [], "Throws": [], "SeeAlso": [], "Permissions": [], "Description": "", "history": "Added in API level 1", "FullName": "public InputStream getContent ()"}, "EntityTemplate(org.apache.http.entity.ContentProducer)": {"Returns": [], "Parameters": [], "Throws": [], "SeeAlso": [], "Permissions": [], "Description": "", "history": "Added in API level 1", "FullName": "public EntityTemplate (ContentProducer contentproducer)"}, "isRepeatable()": {"Returns": [], "Parameters": [], "Throws": [], "SeeAlso": [], "Permissions": [], "Description": "", "history": "Added in API level 1", "FullName": "public boolean isRepeatable ()"}, "consumeContent()": {"Returns": [], "Parameters": [], "Throws": [["@B_java#io#IOException_E@", ""]], "SeeAlso": [], "Permissions": [], "Description": "Does not consume anything. The default implementation does nothing if @B_org#apache#http#HttpEntity#isStreaming_E@ returns false, and throws an exception if it returns true. This removes the burden of implementing an empty method for non-streaming entities.", "history": "Added in API level 1", "FullName": "public void consumeContent ()"}, "isStreaming()": {"Returns": [], "Parameters": [], "Throws": [], "SeeAlso": [], "Permissions": [], "Description": "", "history": "Added in API level 1", "FullName": "public boolean isStreaming ()"}, "writeTo(java.io.OutputStream)": {"Returns": [], "Parameters": [], "Throws": [["@B_java#io#IOException_E@", ""]], "SeeAlso": [], "Permissions": [], "Description": "", "history": "Added in API level 1", "FullName": "public void writeTo (OutputStream outstream)"}, "getContentLength()": {"Returns": [], "Parameters": [], "Throws": [], "SeeAlso": [], "Permissions": [], "Description": "", "history": "Added in API level 1", "FullName": "public long getContentLength ()"}}, "Inheritance": ["@B_org#apache#http#entity#AbstractHttpEntity_E@"], "ClassName": "org.apache.http.entity.EntityTemplate", "ClassDesc": "Please use @B_java#net#URL#openConnection_E@ instead. Please visit Entity that delegates the process of content generation to an abstract content producer."}